odoo10_addon_business_requirement_deliverable_resource_template-10.0.1.0.0-py2.7-nspkg.pth
odoo/addons/business_requirement_deliverable_resource_template/README.rst
odoo/addons/business_requirement_deliverable_resource_template/__init__.py
odoo/addons/business_requirement_deliverable_resource_template/__manifest__.py
odoo/addons/business_requirement_deliverable_resource_template/demo/business_requirement_deliverable_resource_template_demo.xml
odoo/addons/business_requirement_deliverable_resource_template/i18n/sl.po
odoo/addons/business_requirement_deliverable_resource_template/models/__init__.py
odoo/addons/business_requirement_deliverable_resource_template/models/business_requirement_resource_template.py
odoo/addons/business_requirement_deliverable_resource_template/models/product_template.py
odoo/addons/business_requirement_deliverable_resource_template/security/ir.model.access.csv
odoo/addons/business_requirement_deliverable_resource_template/static/description/icon.png
odoo/addons/business_requirement_deliverable_resource_template/static/img/bus_req_default.png
odoo/addons/business_requirement_deliverable_resource_template/static/img/bus_req_default2.png
odoo/addons/business_requirement_deliverable_resource_template/tests/__init__.py
odoo/addons/business_requirement_deliverable_resource_template/tests/test_br_deliverable.py
odoo/addons/business_requirement_deliverable_resource_template/tests/test_br_resource_template.py
odoo/addons/business_requirement_deliverable_resource_template/views/business_requirement_deliverable_default.xml
odoo10_addon_business_requirement_deliverable_resource_template-10.0.1.0.0.dist-info/DESCRIPTION.rst
odoo10_addon_business_requirement_deliverable_resource_template-10.0.1.0.0.dist-info/METADATA
odoo10_addon_business_requirement_deliverable_resource_template-10.0.1.0.0.dist-info/RECORD
odoo10_addon_business_requirement_deliverable_resource_template-10.0.1.0.0.dist-info/WHEEL
odoo10_addon_business_requirement_deliverable_resource_template-10.0.1.0.0.dist-info/metadata.json
odoo10_addon_business_requirement_deliverable_resource_template-10.0.1.0.0.dist-info/namespace_packages.txt
odoo10_addon_business_requirement_deliverable_resource_template-10.0.1.0.0.dist-info/top_level.txt
